pants_backend_mdbook-0.6.0.dist-info/METADATA
pants_backend_mdbook-0.6.0.dist-info/WHEEL
pants_backend_mdbook-0.6.0.dist-info/entry_points.txt
pants_backend_mdbook-0.6.0.dist-info/licenses/LICENSE-MIT.txt
pants_backend_mdbook/__init__.py
pants_backend_mdbook/goals/__init__.py
pants_backend_mdbook/goals/package.py
pants_backend_mdbook/register.py
pants_backend_mdbook/subsystem.py
pants_backend_mdbook/targets.py
pants_backend_mdbook/util_rules/__init__.py
pants_backend_mdbook/util_rules/build.py
pants_backend_mdbook/util_rules/prepare.py
pants_backend_mdbook-0.6.0.dist-info/RECORD
