Metadata-Version: 2.1
Name: pants_backend_mdbook
Version: 0.6.0
Summary: A  MdBook documentation builder plugin for the Pants buildsystem.
Keywords: pantsbuild,pants,backend,mdbook,markdown
Author-Email: Tom Solberg <me@sbg.dev>
License: MIT License
Classifier: Development Status :: 4 - Beta
Classifier: Programming Language :: Python
Classifier: Topic :: Software Development :: Build Tools
Project-URL: Repository, https://github.com/tgolsson/pants-backends
Project-URL: Code, https://github.com/tgolsson/pants-backends/tree/main/pants-plugins/mdbook
Project-URL: Changelog, https://github.com/tgolsson/pants-backends/tree/main/pants-plugins/mdbook/CHANGELOG.md
